pb_tool/__init__.py
pb_tool/pb_tool.py
pb_tool/templates/basic.tmpl
pb_tool/templates/dialog.tmpl
pb_tool/templates/icon.png
pb_tool/templates/pb_tool.tmpl
pb_tool/templates/dialog/__init__.tmpl
pb_tool/templates/dialog/module_name.tmpl
pb_tool/templates/dialog/module_name_dialog.tmpl
pb_tool/templates/dialog/module_name_dialog_base.ui.tmpl
pb_tool/templates/dialog/readme.tmpl
pb_tool/templates/dialog/resources.tmpl
pb_tool/templates/dialog/results.tmpl
pb_tool/templates/minimal/__init__.py
pb_tool/templates/minimal/metadata.txt
pb_tool-3.0.9.dist-info/DESCRIPTION.rst
pb_tool-3.0.9.dist-info/METADATA
pb_tool-3.0.9.dist-info/RECORD
pb_tool-3.0.9.dist-info/WHEEL
pb_tool-3.0.9.dist-info/entry_points.txt
pb_tool-3.0.9.dist-info/metadata.json
pb_tool-3.0.9.dist-info/top_level.txt
